<annotation>
	<folder>images</folder>
	<filename>81.jpg</filename>
	<path>C:\Users\Puter\Desktop\python\models\models\images\81.jpg</path>
	<source>
		<database>Unknown</database>
	</source>
	<size>
		<width>1560</width>
		<height>700</height>
		<depth>3</depth>
	</size>
	<segmented>0</segmented>
	<object>
		<name>enemy</name>
		<pose>Unspecified</pose>
		<truncated>0</truncated>
		<difficult>0</difficult>
		<bndbox>
			<xmin>916</xmin>
			<ymin>66</ymin>
			<xmax>978</xmax>
			<ymax>151</ymax>
		</bndbox>
	</object>
	<object>
		<name>enemy</name>
		<pose>Unspecified</pose>
		<truncated>0</truncated>
		<difficult>0</difficult>
		<bndbox>
			<xmin>636</xmin>
			<ymin>98</ymin>
			<xmax>713</xmax>
			<ymax>182</ymax>
		</bndbox>
	</object>
	<object>
		<name>enemy</name>
		<pose>Unspecified</pose>
		<truncated>0</truncated>
		<difficult>0</difficult>
		<bndbox>
			<xmin>671</xmin>
			<ymin>241</ymin>
			<xmax>750</xmax>
			<ymax>326</ymax>
		</bndbox>
	</object>
	<object>
		<name>enemy</name>
		<pose>Unspecified</pose>
		<truncated>0</truncated>
		<difficult>0</difficult>
		<bndbox>
			<xmin>920</xmin>
			<ymin>264</ymin>
			<xmax>986</xmax>
			<ymax>349</ymax>
		</bndbox>
	</object>
</annotation>
